car2lammpsdata/__init__.py
car2lammpsdata/car2lammpsdata.py
car2lammpsdata-0.0.3.dist-info/METADATA
car2lammpsdata-0.0.3.dist-info/WHEEL
car2lammpsdata-0.0.3.dist-info/entry_points.txt
car2lammpsdata-0.0.3.dist-info/top_level.txt
car2lammpsdata-0.0.3.dist-info/zip-safe
car2lammpsdata-0.0.3.dist-info/RECORD
